lender/__init__.py
lender/application.py
lender/kernel.py
lender/server.py
lender/url.py
lender/handlers/__init__.py
lender/handlers/config.py
lender/handlers/database.py
lender/handlers/fileserver.py
lender/handlers/utils.py
lender/statics/app.js
lender/statics/commonexp.js
lender/statics/favicon.png
lender/statics/notifications.js
lender/statics/style.css
lender/statics/assets/jquery-2.1.4.min.js
lender/statics/assets/blueimp-file-upload/js/demo.js
lender/statics/assets/blueimp-file-upload/js/jquery.fileupload-audio.js
lender/statics/assets/blueimp-file-upload/js/jquery.fileupload-image.js
lender/statics/assets/blueimp-file-upload/js/jquery.fileupload-process.js
lender/statics/assets/blueimp-file-upload/js/jquery.fileupload-ui.js
lender/statics/assets/blueimp-file-upload/js/jquery.fileupload-validate.js
lender/statics/assets/blueimp-file-upload/js/jquery.fileupload-video.js
lender/statics/assets/blueimp-file-upload/js/jquery.fileupload.js
lender/statics/assets/blueimp-file-upload/js/jquery.iframe-transport.js
lender/statics/assets/blueimp-file-upload/js/cors/jquery.postmessage-transport.js
lender/statics/assets/blueimp-file-upload/js/cors/jquery.xdr-transport.js
lender/statics/assets/blueimp-file-upload/js/vendor/jquery.ui.widget.js
lender/statics/assets/bootstrap/css/bootstrap-grid.css
lender/statics/assets/bootstrap/css/bootstrap-grid.css.map
lender/statics/assets/bootstrap/css/bootstrap-grid.min.css
lender/statics/assets/bootstrap/css/bootstrap-grid.min.css.map
lender/statics/assets/bootstrap/css/bootstrap-grid.rtl.css
lender/statics/assets/bootstrap/css/bootstrap-grid.rtl.css.map
lender/statics/assets/bootstrap/css/bootstrap-grid.rtl.min.css
lender/statics/assets/bootstrap/css/bootstrap-grid.rtl.min.css.map
lender/statics/assets/bootstrap/css/bootstrap-icons.css
lender/statics/assets/bootstrap/css/bootstrap-reboot.css
lender/statics/assets/bootstrap/css/bootstrap-reboot.css.map
lender/statics/assets/bootstrap/css/bootstrap-reboot.min.css
lender-1.0.3.dist-info/LICENSE
lender-1.0.3.dist-info/METADATA
lender-1.0.3.dist-info/WHEEL
lender-1.0.3.dist-info/entry_points.txt
lender-1.0.3.dist-info/top_level.txt
lender-1.0.3.dist-info/RECORD
